aws_shepherd/__init__.py
aws_shepherd/__main__.py
aws_shepherd/cli/__init__.py
aws_shepherd/lambda/__init__.py
aws_shepherd/lambda/index.py
aws_shepherd/local.py
aws_shepherd/tester/__init__.py
aws_shepherd-0.2.0.dist-info/entry_points.txt
aws_shepherd-0.2.0.dist-info/WHEEL
aws_shepherd-0.2.0.dist-info/METADATA
aws_shepherd-0.2.0.dist-info/RECORD
